{"v":"5.2.1","fr":30,"ip":0,"op":120,"w":3840,"h":2160,"nm":"darkforestmockup_02","ddd":0,"assets":[{"id":"image_0","w":123,"h":165,"u":"images/","p":"leafies__darkforestmockup_02.png","e":0},{"id":"image_1","w":106,"h":144,"u":"images/","p":"leafies_5_darkforestmockup_02.png","e":0},{"id":"image_2","w":65,"h":86,"u":"images/","p":"leafies_4_darkforestmockup_02.png","e":0},{"id":"image_3","w":83,"h":150,"u":"images/","p":"leafies_3_darkforestmockup_02.png","e":0},{"id":"image_4","w":79,"h":146,"u":"images/","p":"leafies_2_darkforestmockup_02.png","e":0},{"id":"image_5","w":75,"h":123,"u":"images/","p":"leafies1_darkforestmockup_02.png","e":0},{"id":"image_6","w":3840,"h":2160,"u":"images/","p":"Layer_19_darkforestmockup_02.png","e":0},{"id":"comp_0","layers":[{"ddd":0,"ind":1,"ty":2,"nm":"leafies ","refId":"image_0","sr":1,"ks":{"o":{"a":0,"k":100,"ix":11},"r":{"a":1,"k":[{"i":{"x":[0.833],"y":[1]},"o":{"x":[0.333],"y":[0]},"n":["0p833_1_0p333_0"],"t":0,"s":[0],"e":[-8]},{"i":{"x":[0.667],"y":[1]},"o":{"x":[0.167],"y":[0]},"n":["0p667_1_0p167_0"],"t":53,"s":[-8],"e":[0]},{"t":82}],"ix":10},"p":{"a":0,"k":[2508,214.5,0],"ix":2},"a":{"a":0,"k":[34,161.5,0],"ix":1},"s":{"a":0,"k":[100,100,100],"ix":6}},"ao":0,"ip":0,"op":228.978978978979,"st":0,"bm":0},{"ddd":0,"ind":2,"ty":2,"nm":"leafies 5","refId":"image_1","sr":1,"ks":{"o":{"a":0,"k":100,"ix":11},"r":{"a":1,"k":[{"i":{"x":[0.833],"y":[1]},"o":{"x":[0.333],"y":[0]},"n":["0p833_1_0p333_0"],"t":25,"s":[0],"e":[-8]},{"i":{"x":[0.667],"y":[1]},"o":{"x":[0.167],"y":[0]},"n":["0p667_1_0p167_0"],"t":73,"s":[-8],"e":[0]},{"t":119}],"ix":10},"p":{"a":0,"k":[2470.5,146.5,0],"ix":2},"a":{"a":0,"k":[80.5,133.5,0],"ix":1},"s":{"a":0,"k":[100,100,100],"ix":6}},"ao":0,"ip":0,"op":228.978978978979,"st":0,"bm":0},{"ddd":0,"ind":3,"ty":2,"nm":"leafies 4","refId":"image_2","sr":1,"ks":{"o":{"a":0,"k":100,"ix":11},"r":{"a":1,"k":[{"i":{"x":[0.833],"y":[1]},"o":{"x":[0.333],"y":[0]},"n":["0p833_1_0p333_0"],"t":13,"s":[0],"e":[8]},{"i":{"x":[0.667],"y":[1]},"o":{"x":[0.167],"y":[0]},"n":["0p667_1_0p167_0"],"t":64,"s":[8],"e":[0]},{"t":119}],"ix":10},"p":{"a":0,"k":[826.5,166.5,0],"ix":2},"a":{"a":0,"k":[21.058,82.947,0],"ix":1},"s":{"a":0,"k":[100,100,100],"ix":6}},"ao":0,"ip":0,"op":228.978978978979,"st":0,"bm":0},{"ddd":0,"ind":4,"ty":2,"nm":"leafies 3","refId":"image_3","sr":1,"ks":{"o":{"a":0,"k":100,"ix":11},"r":{"a":1,"k":[{"i":{"x":[0.833],"y":[1]},"o":{"x":[0.333],"y":[0]},"n":["0p833_1_0p333_0"],"t":30,"s":[0],"e":[-5]},{"i":{"x":[0.667],"y":[1]},"o":{"x":[0.167],"y":[0]},"n":["0p667_1_0p167_0"],"t":60,"s":[-5],"e":[0]},{"t":90}],"ix":10},"p":{"a":0,"k":[758,180.5,0],"ix":2},"a":{"a":0,"k":[42,151.5,0],"ix":1},"s":{"a":0,"k":[100,100,100],"ix":6}},"ao":0,"ip":0,"op":228.978978978979,"st":0,"bm":0},{"ddd":0,"ind":5,"ty":2,"nm":"leafies 2","refId":"image_4","sr":1,"ks":{"o":{"a":0,"k":100,"ix":11},"r":{"a":1,"k":[{"i":{"x":[0.833],"y":[1]},"o":{"x":[0.333],"y":[0]},"n":["0p833_1_0p333_0"],"t":7,"s":[0],"e":[11]},{"i":{"x":[0.667],"y":[1]},"o":{"x":[0.167],"y":[0]},"n":["0p667_1_0p167_0"],"t":72,"s":[11],"e":[0]},{"t":119}],"ix":10},"p":{"a":0,"k":[487.5,169,0],"ix":2},"a":{"a":0,"k":[45.316,139,0],"ix":1},"s":{"a":0,"k":[100,100,100],"ix":6}},"ao":0,"ip":0,"op":228.978978978979,"st":0,"bm":0},{"ddd":0,"ind":6,"ty":2,"nm":"leafies1","refId":"image_5","sr":1,"ks":{"o":{"a":0,"k":100,"ix":11},"r":{"a":1,"k":[{"i":{"x":[0.833],"y":[1]},"o":{"x":[0.333],"y":[0]},"n":["0p833_1_0p333_0"],"t":18,"s":[0],"e":[8]},{"i":{"x":[0.667],"y":[1]},"o":{"x":[0.167],"y":[0]},"n":["0p667_1_0p167_0"],"t":85,"s":[8],"e":[0]},{"t":119}],"ix":10},"p":{"a":0,"k":[413.5,153.5,0],"ix":2},"a":{"a":0,"k":[63.5,133.5,0],"ix":1},"s":{"a":0,"k":[100,100,100],"ix":6}},"ao":0,"ip":0,"op":228.978978978979,"st":0,"bm":0},{"ddd":0,"ind":7,"ty":2,"nm":"Layer 19","refId":"image_6","sr":1,"ks":{"o":{"a":0,"k":100,"ix":11},"r":{"a":0,"k":0,"ix":10},"p":{"a":0,"k":[1919.5,1079.5,0],"ix":2},"a":{"a":0,"k":[1920,1080,0],"ix":1},"s":{"a":0,"k":[101,101,100],"ix":6}},"ao":0,"ip":0,"op":228.978978978979,"st":0,"bm":0}]}],"layers":[{"ddd":0,"ind":1,"ty":0,"nm":"Bottom Layer final","refId":"comp_0","sr":1,"ks":{"o":{"a":0,"k":100,"ix":11},"r":{"a":0,"k":0,"ix":10},"p":{"a":0,"k":[1920,1080,0],"ix":2},"a":{"a":0,"k":[1920,1080,0],"ix":1},"s":{"a":0,"k":[100,100,100],"ix":6}},"ao":0,"w":3840,"h":2160,"ip":0,"op":120,"st":0,"bm":0}],"markers":[]}