{"v":"5.2.1","fr":30,"ip":0,"op":150,"w":3840,"h":3577,"nm":"FinalBattle_New","ddd":0,"assets":[{"id":"image_0","w":910,"h":352,"u":"images/","p":"right_hair_FinalBattle_New.png","e":0},{"id":"image_1","w":486,"h":219,"u":"images/","p":"right_hair_copy_2_FinalBattle_New.png","e":0},{"id":"image_2","w":695,"h":430,"u":"images/","p":"right_hair_copy_FinalBattle_New.png","e":0},{"id":"image_3","w":912,"h":278,"u":"images/","p":"right_hair_copy_3_FinalBattle_New.png","e":0},{"id":"image_4","w":209,"h":472,"u":"images/","p":"left_hair_FinalBattle_New.png","e":0},{"id":"image_5","w":202,"h":614,"u":"images/","p":"left_hair_copy_2_FinalBattle_New.png","e":0},{"id":"image_6","w":668,"h":839,"u":"images/","p":"left_hair_copy_FinalBattle_New.png","e":0},{"id":"image_7","w":337,"h":448,"u":"images/","p":"left_hair_copy_3_FinalBattle_New.png","e":0},{"id":"comp_0","layers":[{"ddd":0,"ind":6,"ty":3,"nm":"Head","sr":1,"ks":{"o":{"a":0,"k":100,"ix":11},"r":{"a":1,"k":[{"i":{"x":[0.833],"y":[1]},"o":{"x":[0.333],"y":[0]},"n":["0p833_1_0p333_0"],"t":6,"s":[0],"e":[7]},{"i":{"x":[0.833],"y":[1]},"o":{"x":[0.167],"y":[0]},"n":["0p833_1_0p167_0"],"t":36,"s":[7],"e":[9]},{"i":{"x":[0.667],"y":[1]},"o":{"x":[0.167],"y":[0]},"n":["0p667_1_0p167_0"],"t":96,"s":[9],"e":[0]},{"t":156}],"ix":10},"p":{"a":0,"k":[2538,1278,0],"ix":2},"a":{"a":0,"k":[238,593,0],"ix":1},"s":{"a":0,"k":[100,100,100],"ix":6}},"ao":0,"ip":6,"op":156,"st":6,"bm":0},{"ddd":0,"ind":20,"ty":0,"nm":"right hair","parent":21,"refId":"comp_1","sr":1,"ks":{"o":{"a":0,"k":100,"ix":11},"r":{"a":0,"k":0,"ix":10},"p":{"a":0,"k":[2847.911,612.5,0],"ix":2},"a":{"a":0,"k":[2847.911,612.5,0],"ix":1},"s":{"a":0,"k":[100,100,100],"ix":6}},"ao":0,"w":3840,"h":2577,"ip":6,"op":156,"st":6,"bm":0},{"ddd":0,"ind":21,"ty":0,"nm":"left hair","parent":6,"refId":"comp_2","sr":1,"ks":{"o":{"a":0,"k":100,"ix":11},"r":{"a":1,"k":[{"i":{"x":[0.667],"y":[1]},"o":{"x":[0.333],"y":[0]},"n":["0p667_1_0p333_0"],"t":6,"s":[0],"e":[-5]},{"i":{"x":[0.563],"y":[0.766]},"o":{"x":[0.185],"y":[0]},"n":["0p563_0p766_0p185_0"],"t":38,"s":[-5],"e":[-7]},{"i":{"x":[0.842],"y":[1]},"o":{"x":[0.373],"y":[0.888]},"n":["0p842_1_0p373_0p888"],"t":56,"s":[-7],"e":[-8]},{"i":{"x":[0.667],"y":[1]},"o":{"x":[0.167],"y":[0]},"n":["0p667_1_0p167_0"],"t":96,"s":[-8],"e":[0]},{"t":155}],"ix":10},"p":{"a":0,"k":[200,296.5,0],"ix":2},"a":{"a":0,"k":[2500,658.5,0],"ix":1},"s":{"a":0,"k":[100,100,100],"ix":6}},"ao":0,"w":3840,"h":2577,"ip":6,"op":156,"st":6,"bm":0}]},{"id":"comp_1","layers":[{"ddd":0,"ind":1,"ty":2,"nm":"right hair 2","refId":"image_0","sr":1,"ks":{"o":{"a":0,"k":100,"ix":11},"r":{"a":0,"k":0,"ix":10},"p":{"a":0,"k":[3062,883,0],"ix":2},"a":{"a":0,"k":[455,176,0],"ix":1},"s":{"a":0,"k":[100,100,100],"ix":6}},"ao":0,"ip":0,"op":150,"st":0,"bm":0},{"ddd":0,"ind":2,"ty":2,"nm":"right hair copy 6","refId":"image_1","sr":1,"ks":{"o":{"a":0,"k":100,"ix":11},"r":{"a":0,"k":0,"ix":10},"p":{"a":0,"k":[2985,597.5,0],"ix":2},"a":{"a":0,"k":[243,109.5,0],"ix":1},"s":{"a":0,"k":[100,100,100],"ix":6}},"ao":0,"ip":0,"op":150,"st":0,"bm":0},{"ddd":0,"ind":3,"ty":2,"nm":"right hair copy 5","refId":"image_2","sr":1,"ks":{"o":{"a":0,"k":100,"ix":11},"r":{"a":0,"k":0,"ix":10},"p":{"a":0,"k":[3019.5,1544,0],"ix":2},"a":{"a":0,"k":[347.5,215,0],"ix":1},"s":{"a":0,"k":[100,100,100],"ix":6}},"ao":0,"ip":0,"op":150,"st":0,"bm":0},{"ddd":0,"ind":4,"ty":2,"nm":"right hair copy 4","refId":"image_3","sr":1,"ks":{"o":{"a":0,"k":100,"ix":11},"r":{"a":0,"k":0,"ix":10},"p":{"a":0,"k":[3061,1194,0],"ix":2},"a":{"a":0,"k":[456,139,0],"ix":1},"s":{"a":0,"k":[100,100,100],"ix":6}},"ao":0,"ip":0,"op":150,"st":0,"bm":0}]},{"id":"comp_2","layers":[{"ddd":0,"ind":1,"ty":2,"nm":"left hair 2","refId":"image_4","sr":1,"ks":{"o":{"a":0,"k":100,"ix":11},"r":{"a":0,"k":0,"ix":10},"p":{"a":0,"k":[2194.5,1116,0],"ix":2},"a":{"a":0,"k":[104.5,236,0],"ix":1},"s":{"a":0,"k":[100,100,100],"ix":6}},"ao":0,"ip":0,"op":150,"st":0,"bm":0},{"ddd":0,"ind":2,"ty":2,"nm":"left hair copy 6","refId":"image_5","sr":1,"ks":{"o":{"a":0,"k":100,"ix":11},"r":{"a":0,"k":0,"ix":10},"p":{"a":0,"k":[1989,1165,0],"ix":2},"a":{"a":0,"k":[101,307,0],"ix":1},"s":{"a":0,"k":[100,100,100],"ix":6}},"ao":0,"ip":0,"op":150,"st":0,"bm":0},{"ddd":0,"ind":3,"ty":2,"nm":"left hair copy 5","refId":"image_6","sr":1,"ks":{"o":{"a":0,"k":100,"ix":11},"r":{"a":0,"k":0,"ix":10},"p":{"a":0,"k":[1554,1280.5,0],"ix":2},"a":{"a":0,"k":[334,419.5,0],"ix":1},"s":{"a":0,"k":[100,100,100],"ix":6}},"ao":0,"ip":0,"op":150,"st":0,"bm":0},{"ddd":0,"ind":4,"ty":2,"nm":"left hair copy 4","refId":"image_7","sr":1,"ks":{"o":{"a":0,"k":100,"ix":11},"r":{"a":0,"k":0,"ix":10},"p":{"a":0,"k":[1387.5,1477,0],"ix":2},"a":{"a":0,"k":[168.5,224,0],"ix":1},"s":{"a":0,"k":[100,100,100],"ix":6}},"ao":0,"ip":0,"op":150,"st":0,"bm":0}]}],"layers":[{"ddd":0,"ind":6,"ty":0,"nm":"Lady Luck (Top)","refId":"comp_0","sr":1,"ks":{"o":{"a":0,"k":100,"ix":11},"r":{"a":0,"k":0,"ix":10},"p":{"a":0,"k":[1920,1383.5,0],"ix":2},"a":{"a":0,"k":[1920,1611.5,0],"ix":1},"s":{"a":0,"k":[100,100,100],"ix":6}},"ao":0,"w":3840,"h":3223,"ip":-6,"op":156,"st":-6,"bm":0}],"markers":[]}